{"cameraMode":{"drawMode":0,"name":"Shaded","section":"Shading Mode"},"sceneLighting":true,"audioPlay":false,"sceneViewState":{"showFog":true,"showMaterialUpdate":false,"showSkybox":true,"showFlares":true,"showImageEffects":true,"showParticleSystems":true,"showVisualEffectGraphs":true,"m_FxEnabled":true},"in2DMode":false,"pivot":{"x":0.22713889181613923,"y":3.8889074325561525,"z":1.1557066440582276},"rotation":{"x":-0.1593838334083557,"y":-0.7173230648040772,"z":0.1743883490562439,"w":-0.655501127243042},"size":1.0414214134216309,"orthographic":false}